{
"categories": [
{
"id": "entertainment",
"name": "Fun & Entertainment",
"icon": "fa-gamepad",
"places": [
{
"name": "Cypress Pointe Pier",
"address": "101 Boardwalk Drive",
"community": "Cypress Pointe",
"slurl": "https://maps.secondlife.com/",
"website": "https://cypresspointesl.com",
"phone": "(555) 555-1001",
"image": "https://placehold.co/1280x720",
"description": "A lively waterfront destination featuring seasonal events, fishing, sightseeing, and coastal views."
}
]
},
{
"id": "restaurants",
"name": "Restaurants",
"icon": "fa-utensils",
"places": [
{
"name": "The Valley Bistro",
"address": "45 Main Street",
"community": "Grimlocke",
"slurl": "https://maps.secondlife.com/",
"website": "https://townofgrimlocke.com",
"phone": "(555) 555-2001",
"contact": "Jacob Fear (dark.nebula)", 
"image": "https://placehold.co/1280x720",
"description": "A cozy downtown restaurant offering fresh meals, coffee, and a welcoming atmosphere."
}
]
},
{
"id": "stores",
"name": "Stores",
"icon": "fa-shopping-bag",
"places": [
{
"name": "Ponderosa Outfitters",
"address": "210 Timberline Way",
"community": "Cypress Pointe",
"slurl": "https://maps.secondlife.com/",
"website": "https://cypresspointesl.com",
"phone": "(555) 555-3001",
"contact": "Jacob Fear (dark.nebula)", 
"image": "https://placehold.co/1280x720",
"description": "Outdoor gear, camping supplies, and equipment for every adventure."
}
]
},
{
"id": "services",
"name": "Public Services",
"icon": "fa-shield-halved",
"places": [
{
"name": "White Valley Sheriff's Office",
"address": "100 Justice Way",
"community": "Grimlocke",
"slurl": "https://maps.secondlife.com/",
"website": "https://townofgrimlocke.com/applications/wvso",
"phone": "911",
"contact": "Jacob Fear (dark.nebula)", 
"image": "https://placehold.co/1280x720",
"description": "Primary law enforcement agency serving White Valley County."
},
{
"name": "White Valley Medical Center",
"address": "500 Health Drive",
"community": "White Valley",
"slurl": "https://maps.secondlife.com/",
"website": "https://townofgrimlocke.com/applications/wvmc",
"phone": "911",
"contact": "Jacob Fear (dark.nebula)", 
"image": "https://placehold.co/1280x720",
"description": "Regional medical center providing emergency and inpatient care."
}
]
}
]
}
